whereto/__init__.py
whereto/app.py
whereto/parser.py
whereto/rules.py
whereto/tests/__init__.py
whereto/tests/base.py
whereto/tests/test_app.py
whereto/tests/test_parser.py
whereto/tests/test_rules.py
whereto-0.5.0.dist-info/licenses/AUTHORS
whereto-0.5.0.dist-info/licenses/LICENSE
whereto-0.5.0.dist-info/METADATA
whereto-0.5.0.dist-info/WHEEL
whereto-0.5.0.dist-info/entry_points.txt
whereto-0.5.0.dist-info/pbr.json
whereto-0.5.0.dist-info/top_level.txt
whereto-0.5.0.dist-info/RECORD
